setup.py
py_search_game_algo.egg-info/PKG-INFO
py_search_game_algo.egg-info/SOURCES.txt
py_search_game_algo.egg-info/dependency_links.txt
py_search_game_algo.egg-info/requires.txt
py_search_game_algo.egg-info/top_level.txt
py_search_game_algo/searches/__init__.py
py_search_game_algo/searches/advertisal.py
py_search_game_algo/searches/informed.py
py_search_game_algo/searches/local.py
py_search_game_algo/searches/uninformed.py
py_search_game_algo/utile/__init__.py
py_search_game_algo/utile/problem.py
py_search_game_algo/utile/util.py