Metadata-Version: 2.1
Name: py-search-game-algo
Version: 1.0
Summary: py_search_game_algo
License: UNKNOWN
Platform: UNKNOWN
